README.md
setup.cfg
setup.py
drunk_man/__init__.py
drunk_man.egg-info/PKG-INFO
drunk_man.egg-info/SOURCES.txt
drunk_man.egg-info/dependency_links.txt
drunk_man.egg-info/requires.txt
drunk_man.egg-info/top_level.txt