Metadata-Version: 1.1
Name: drunk-man
Version: 6.9
Summary: This repo was made as a joke for our drunk friend. This repo is totally useless, just like our drunk friend.
Home-page: https://github.com/Chiggy-Playz/drunk-man
Author: Chiggy#6420
Author-email: support@xeprah.com
License: MIT
Download-URL: https://github.com/user/reponame/archive/v_01.tar.gz
Keywords: drunk,man,drunk-man,drunk_man,useless,python,discord.py
Platform: UNKNOWN
Classifier: Development Status :: 5 - Production/Stable
Classifier: Intended Audience :: Developers
Classifier: Topic :: Software Development :: Build Tools
Classifier: License :: OSI Approved :: MIT License
Classifier: Programming Language :: Python :: 3
Classifier: Programming Language :: Python :: 3.4
Classifier: Programming Language :: Python :: 3.5
Classifier: Programming Language :: Python :: 3.6
Classifier: Programming Language :: Python :: 3.7
Classifier: Programming Language :: Python :: 3.8
